nonebot_plugin_random_stereotypes-0.5.0.dist-info/METADATA
nonebot_plugin_random_stereotypes-0.5.0.dist-info/WHEEL
nonebot_plugin_random_stereotypes-0.5.0.dist-info/entry_points.txt
nonebot_plugin_random_stereotypes-0.5.0.dist-info/licenses/LICENSE
nonebot_plugin_random_stereotypes/__init__.py
nonebot_plugin_random_stereotypes/__main__.py
nonebot_plugin_random_stereotypes/config.py
nonebot_plugin_random_stereotypes/cool_down.py
nonebot_plugin_random_stereotypes/data.py
nonebot_plugin_random_stereotypes/meme/__init__.py
nonebot_plugin_random_stereotypes/meme/base.py
nonebot_plugin_random_stereotypes/meme/impl/__init__.py
nonebot_plugin_random_stereotypes/meme/impl/api.py
nonebot_plugin_random_stereotypes/meme/impl/embed.py
nonebot_plugin_random_stereotypes/meme/random.py
nonebot_plugin_random_stereotypes/utils.py
nonebot_plugin_random_stereotypes-0.5.0.dist-info/RECORD
