Metadata-Version: 2.1
Name: nonebot-plugin-random-stereotypes
Version: 0.5.0
Summary: 基于Nonebot2的发病语录插件
Author-Email: Ikaros <327209194@qq.com>, LgCookie <lgc2333@126.com>
License: MIT
Project-URL: homepage, https://github.com/lgc-NB2Dev/nonebot-plugin-random-stereotypes
Project-URL: repository, https://github.com/lgc-NB2Dev/nonebot-plugin-random-stereotypes
Project-URL: documentation, https://github.com/lgc-NB2Dev/nonebot-plugin-random-stereotypes/blob/master/README.md
Requires-Python: <4.0,>=3.9
Requires-Dist: nonebot2>=2.4.2
Requires-Dist: nonebot-plugin-alconna>=0.58.0
Requires-Dist: nonebot-plugin-waiter>=0.8.1
Requires-Dist: cookit[pyd]>=0.11.6
Requires-Dist: nonebot-plugin-uninfo>=0.7.4
Provides-Extra: meme
Requires-Dist: meme-generator>=0.2.1; extra == "meme"
Provides-Extra: meme-api
Requires-Dist: nonebot-plugin-memes-api>=0.5.1; extra == "meme-api"
